Metadata-Version: 1.1
Name: dtool-lookup-server-annotation-filter-plugin
Version: 0.1.1
Summary: Extend dtool-lookup-server with ability to filter by annotations
Home-page: https://github.com/jic-dtool/dtool-lookup-server-annotation-filter-plugin
Author: Tjelvar Olsson
Author-email: tjelvar.olsson@gmail.com
License: MIT
Download-URL: https://github.com/jic-dtool/dtool-lookup-server-annotation-filter-plugin/tarball/0.1.1
Platform: UNKNOWN
